<?xml version="1.0" encoding="UTF-8"?>
<items>
<playlist_name><![CDATA[]]></playlist_name>

<channel>
		<title><![CDATA[Into The Badlands 3.SEZON 1.Bölüm]]></title>
		<logo_30x30><![CDATA[http://www.picz.ge/img/s2/1701/3/8/8b8da7efb813.jpg]]></logo_30x30>
		<description><![CDATA[<img http://www.picz.ge/img/s2/1701/3/8/8b8da7efb813.jpg">]]></description>
		<stream_url><![CDATA[https://odnoklassniki.ru/videoembed/955507870253]]></stream_url>
		</channel>
<channel>
		<title><![CDATA[Into The Badlands 3.SEZON 4.Bölüm]]></title>
		<logo_30x30><![CDATA[http://www.picz.ge/img/s2/1701/3/8/8b8da7efb813.jpg]]></logo_30x30>
		<description><![CDATA[<img http://www.picz.ge/img/s2/1701/3/8/8b8da7efb813.jpg">]]></description>
		<playlist_url><![CDATA[https://my.cloudme.com/v1/ws2/:sorgumurat/:sezon_3.4/sezon_3.4.xml?dl=sezon_3.4.xml]]></playlist_url>>
		</channel>
<channel>
		<title><![CDATA[Into The Badlands 3.SEZON 5.Bölüm]]></title>
		<logo_30x30><![CDATA[http://www.picz.ge/img/s2/1701/3/8/8b8da7efb813.jpg]]></logo_30x30>
		<description><![CDATA[<img http://www.picz.ge/img/s2/1701/3/8/8b8da7efb813.jpg">]]></description>
		<playlist_url><![CDATA[https://my.cloudme.com/v1/ws2/:sorgumurat/:sezon_3.5/sezon_3.5.xml?dl=sezon_3.5.xml]]></playlist_url>>
		</channel>
<channel>
		<title><![CDATA[Into The Badlands 3.SEZON 6.Bölüm]]></title>
		<logo_30x30><![CDATA[http://www.picz.ge/img/s2/1701/3/8/8b8da7efb813.jpg]]></logo_30x30>
		<description><![CDATA[<img http://www.picz.ge/img/s2/1701/3/8/8b8da7efb813.jpg">]]></description>
		<playlist_url><![CDATA[https://my.cloudme.com/v1/ws2/:sorgumurat/:sezon_3.6/sezon_3.6.xml?dl=sezon_3.6.xml]]></playlist_url>>
		</channel>
<channel>
		<title><![CDATA[Into The Badlands 3.SEZON 7.Bölüm]]></title>
		<logo_30x30><![CDATA[http://www.picz.ge/img/s2/1701/3/8/8b8da7efb813.jpg]]></logo_30x30>
		<description><![CDATA[<img http://www.picz.ge/img/s2/1701/3/8/8b8da7efb813.jpg">]]></description>
		<playlist_url><![CDATA[https://my.cloudme.com/v1/ws2/:sorgumurat/:sezon_3.7/sezon_3.7.xml?dl=sezon_3.7.xml]]></playlist_url>>
		</channel>
</items>
